jjtemplate.py
jjtemplate-0.9.0.dist-info/LICENSE
jjtemplate-0.9.0.dist-info/METADATA
jjtemplate-0.9.0.dist-info/WHEEL
jjtemplate-0.9.0.dist-info/entry_points.txt
jjtemplate-0.9.0.dist-info/top_level.txt
jjtemplate-0.9.0.dist-info/RECORD
