Metadata-Version: 2.1
Name: jjtemplate
Version: 0.9.0
Summary: Jinja2 Templating with JSON files
Author-email: Masaaki Shibata <mshibata@emptypage.jp>
Project-URL: Repository, https://bitbucket.org/emptypage/jjtemplate/
Keywords: jinja2,json,template,templating
Classifier: Development Status :: 4 - Beta
Classifier: Environment :: Console
Classifier: Intended Audience :: Developers
Classifier: Intended Audience :: Information Technology
Classifier: Intended Audience :: System Administrators
Classifier: License :: CC0 1.0 Universal (CC0 1.0) Public Domain Dedication
Classifier: License :: Public Domain
Classifier: Operating System :: OS Independent
Classifier: Programming Language :: Python :: 3
Classifier: Programming Language :: Python :: 3.9
Classifier: Programming Language :: Python :: 3.10
Classifier: Programming Language :: Python :: 3.12
Classifier: Topic :: Text Processing
Requires-Python: >=3.9
License-File: LICENSE
Requires-Dist: jinja2
